{
  "sections": {
    "main": {
      "type": "loob-page",
      "settings": {
      }
    },
    "1642198809efaac2ac": {
      "type": "image-with-text",
      "blocks": {
        "16421988099592a724-0": {
          "type": "heading",
          "settings": {
            "heading": "Image with text"
          }
        },
        "16421988099592a724-1": {
          "type": "text",
          "settings": {
            "text": "<p>Pair text with an image to focus on your chosen product, collection, or blog post. Add details on availability, style, or even provide a review.<\/p>"
          }
        },
        "16421988099592a724-2": {
          "type": "button",
          "settings": {
            "button_label": "Button label",
            "button_link": ""
          }
        }
      },
      "block_order": [
        "16421988099592a724-0",
        "16421988099592a724-1",
        "16421988099592a724-2"
      ],
      "settings": {
        "height": "adapt",
        "color_scheme": "background-1",
        "layout": "image_first"
      }
    },
    "164201147954c36fb9": {
      "type": "collection-list",
      "blocks": {
        "16420114797d203add-1": {
          "type": "featured_collection",
          "settings": {
            "collection": "soft-grease"
          }
        },
        "16420114797d203add-0": {
          "type": "featured_collection",
          "settings": {
            "collection": "lube-for-key-stabilizer-wires"
          }
        },
        "16420114797d203add-2": {
          "type": "featured_collection",
          "settings": {
            "collection": "oils"
          }
        }
      },
      "block_order": [
        "16420114797d203add-1",
        "16420114797d203add-0",
        "16420114797d203add-2"
      ],
      "settings": {
        "title": "Collections",
        "image_ratio": "square",
        "color_scheme": "background-1",
        "swipe_on_mobile": false,
        "image_padding": false,
        "show_view_all": false
      }
    }
  },
  "order": [
    "main",
    "1642198809efaac2ac",
    "164201147954c36fb9"
  ]
}
